setup.py
user_feature_pipeline.egg-info/PKG-INFO
user_feature_pipeline.egg-info/SOURCES.txt
user_feature_pipeline.egg-info/dependency_links.txt
user_feature_pipeline.egg-info/top_level.txt
user_feature_utils/__init__.py
user_feature_utils/feature_creation_utils.py
user_feature_utils/user_feature_creation_transforms.py